{
  "contractName": "Faucet.sol:Faucet",
  "compilerVersion": "0.8.28",
  "settings": {
    "evmVersion": "cancun",
    "viaIR": true,
    "optimizer": {
      "enabled": true,
      "runs": 200
    }
  },
  "sources": {
    "Faucet.sol": {
      "urls": ["lib/Faucet.sol"]
    },
    "SmartAccount.sol": {
      "urls": ["lib/SmartAccount.sol"]
    },
    "NilTokenBase.sol": {
      "urls": ["lib/NilTokenBase.sol"]
    },
    "Nil.sol": {
      "urls": ["lib/Nil.sol"]
    },
    "Relayer.sol": {
      "urls": ["lib/Relayer.sol"]
    },
    "NilTokenManager.sol": {
      "urls": ["lib/NilTokenManager.sol"]
    },
    "IterableMapping.sol": {
      "urls": ["lib/IterableMapping.sol"]
    },
    "system/console.sol": {
      "urls": ["system/console.sol"]
    }
  }
}
